README.txt
setup.cfg
setup.py
collective/__init__.py
collective.synchro.egg-info/PKG-INFO
collective.synchro.egg-info/SOURCES.txt
collective.synchro.egg-info/dependency_links.txt
collective.synchro.egg-info/entry_points.txt
collective.synchro.egg-info/namespace_packages.txt
collective.synchro.egg-info/not-zip-safe
collective.synchro.egg-info/requires.txt
collective.synchro.egg-info/top_level.txt
collective/synchro/README.txt
collective/synchro/__init__.py
collective/synchro/adapters.zcml
collective/synchro/config.py
collective/synchro/configure.zcml
collective/synchro/data.py
collective/synchro/events.py
collective/synchro/events.zcml
collective/synchro/permissions.py
collective/synchro/permissions.zcml
collective/synchro/profiles.zcml
collective/synchro/queues.py
collective/synchro/tests.py
collective/synchro/tools.py
collective/synchro/utils.py
collective/synchro/version.txt
collective/synchro/browser/__init__.py
collective/synchro/browser/configure.zcml
collective/synchro/browser/images/portal_synchro.png
collective/synchro/buildout/README.txt
collective/synchro/buildout/plone_25/README.txt
collective/synchro/buildout/plone_25/bootstrap.py
collective/synchro/buildout/plone_25/buildout.cfg
collective/synchro/buildout/plone_30/README.txt
collective/synchro/buildout/plone_30/bootstrap.py
collective/synchro/buildout/plone_30/buildout.cfg
collective/synchro/doctests/browser.txt
collective/synchro/doctests/event.txt
collective/synchro/doctests/export.txt
collective/synchro/doctests/export_fss.txt
collective/synchro/doctests/import.txt
collective/synchro/doctests/synchro.txt
collective/synchro/interfaces/__init__.py
collective/synchro/interfaces/bbb.py
collective/synchro/interfaces/events.py
collective/synchro/interfaces/plugin.py
collective/synchro/interfaces/queues.py
collective/synchro/interfaces/tool.py
collective/synchro/plugins/__init__.py
collective/synchro/plugins/delete.py
collective/synchro/plugins/fss.py
collective/synchro/plugins/zexp.py
collective/synchro/profiles/default/componentregistry.xml
collective/synchro/profiles/default/toolset.xml
collective/synchro/scripts/__init__.py
collective/synchro/scripts/import_queue.py
collective/synchro/scripts/synchro_queues.py
collective/synchro/scripts/utils.py
docs/HISTORY.txt
docs/INSTALL.txt
docs/LICENSE.GPL
docs/LICENSE.txt