Metadata-Version: 1.0
Name: collective.synchro
Version: 1.0.1
Summary: synchronize content between plone instance
Home-page: https://svn.plone.org/svn/collective/collective.synchro
Author: Ingeniweb
Author-email: support@ingeniweb.com
License: GPL
Keywords: synchronisation export import plone
Platform: UNKNOWN
Classifier: Framework :: Plone
Classifier: Programming Language :: Python
Classifier: Topic :: Software Development :: Libraries :: Python Modules
